styleframe/__init__.py
styleframe/container.py
styleframe/deprecations.py
styleframe/series.py
styleframe/style_frame.py
styleframe/styler.py
styleframe/utils.py
styleframe/version.py
styleframe/command_line/__init__.py
styleframe/command_line/commandline.py
styleframe/command_line/tests/__init__.py
styleframe/command_line/tests/commandline_tests.py
styleframe/command_line/tests/json_schema.py
styleframe/command_line/tests/test_json.json
styleframe/command_line/tests/test_json_string.json
styleframe/tests/__init__.py
styleframe/tests/container_tests.py
styleframe/tests/series_tests.py
styleframe/tests/style_frame_tests.py
styleframe/tests/styler_tests.py
styleframe/tests/tests.py
styleframe-3.0.6.dist-info/LICENSE
styleframe-3.0.6.dist-info/METADATA
styleframe-3.0.6.dist-info/WHEEL
styleframe-3.0.6.dist-info/entry_points.txt
styleframe-3.0.6.dist-info/top_level.txt
styleframe-3.0.6.dist-info/RECORD
